LICENSE
MANIFEST.in
README.md
setup.py
django_generic_m2m_field.egg-info/PKG-INFO
django_generic_m2m_field.egg-info/SOURCES.txt
django_generic_m2m_field.egg-info/dependency_links.txt
django_generic_m2m_field.egg-info/not-zip-safe
django_generic_m2m_field.egg-info/requires.txt
django_generic_m2m_field.egg-info/top_level.txt
example/__init__.py
example/manage.py
example/urls.py
example/wsgi.py
example/apps/__init__.py
example/apps/app/__init__.py
example/apps/app/models.py
example/apps/app/migrations/0001_initial.py
example/apps/app/migrations/0002_auto_20201007_1210.py
example/apps/app/migrations/0003_auto_20210604_1406.py
example/apps/app/migrations/__init__.py
example/apps/app/tests/__init__.py
example/settings/__init__.py
example/settings/base.py
example/settings/settings.py
generic_m2m_field/__init__.py
generic_m2m_field/models.py