Metadata-Version: 1.1
Name: django-generic-m2m-field
Version: 0.0.7
Summary: Django generic many to many field library.
Home-page: https://github.com/druids/django-generic-m2m-field
Author: Lubos Matl
Author-email: matllubos@gmail.com
License: MIT
Keywords: django,fields,generic
Platform: UNKNOWN
Classifier: Development Status :: 3 - Alpha
Classifier: Environment :: Web Environment
Classifier: Framework :: Django
Classifier: Intended Audience :: Developers
Classifier: Intended Audience :: End Users/Desktop
Classifier: License :: OSI Approved :: MIT License
Classifier: Natural Language :: Czech
Classifier: Operating System :: OS Independent
Classifier: Programming Language :: Python
Classifier: Topic :: Internet :: WWW/HTTP :: Dynamic Content
Classifier: Topic :: Internet :: WWW/HTTP :: Site Management
